librarypy/__init__.py
librarypy-0.0.1.dist-info/METADATA
librarypy-0.0.1.dist-info/WHEEL
librarypy-0.0.1.dist-info/top_level.txt
librarypy-0.0.1.dist-info/RECORD
