Metadata-Version: 2.1
Name: librarypy
Version: 0.0.1
Summary: LibraryPy is a Python library built for Python 3.11.0.
Home-page: https://github.com/IO-Teknikk/LibraryPy
Author: IO Teknikk
Author-email: mr.edwin74@gmail.com
Project-URL: Bug Tracker, https://github.com/IO-Teknikk/LibraryPy/issues
Classifier: Programming Language :: Python :: 3
Classifier: License :: OSI Approved :: MIT License
Classifier: Operating System :: OS Independent
Requires-Python: >=3.11
